keras_applications/__init__.py
keras_applications/densenet.py
keras_applications/imagenet_utils.py
keras_applications/inception_resnet_v2.py
keras_applications/inception_v3.py
keras_applications/mobilenet.py
keras_applications/mobilenet_v2.py
keras_applications/nasnet.py
keras_applications/resnet.py
keras_applications/resnet50.py
keras_applications/resnet_common.py
keras_applications/resnet_v2.py
keras_applications/resnext.py
keras_applications/vgg16.py
keras_applications/vgg19.py
keras_applications/xception.py
Keras_Applications-1.0.7.dist-info/LICENSE
Keras_Applications-1.0.7.dist-info/METADATA
Keras_Applications-1.0.7.dist-info/WHEEL
Keras_Applications-1.0.7.dist-info/top_level.txt
Keras_Applications-1.0.7.dist-info/RECORD
