Metadata-Version: 2.1
Name: Keras_Applications
Version: 1.0.7
Summary: Reference implementations of popular deep learning models
Home-page: https://github.com/keras-team/keras-applications
Author: Keras Team
License: MIT
Download-URL: https://github.com/keras-team/keras-applications/tarball/1.0.7
Platform: UNKNOWN
Classifier: Development Status :: 5 - Production/Stable
Classifier: Intended Audience :: Developers
Classifier: Intended Audience :: Education
Classifier: Intended Audience :: Science/Research
Classifier: License :: OSI Approved :: MIT License
Classifier: Programming Language :: Python :: 2
Classifier: Programming Language :: Python :: 2.7
Classifier: Programming Language :: Python :: 3
Classifier: Programming Language :: Python :: 3.6
Classifier: Topic :: Software Development :: Libraries
Classifier: Topic :: Software Development :: Libraries :: Python Modules
Provides-Extra: tests
